ferret.py
ferret-0.8.0.dist-info/entry_points.txt
ferret-0.8.0.dist-info/LICENSE
ferret-0.8.0.dist-info/WHEEL
ferret-0.8.0.dist-info/METADATA
ferret-0.8.0.dist-info/RECORD
