Metadata-Version: 1.2
Name: ferret
Version: 0.8.0
Summary: a snake that runs. execute python files without packaging or installation
Home-page: https://github.com/jelford/ferret
License: MIT
Author: James Elford
Author-email: james.p.elford@gmail.com
Requires-Python: ~=3.6
